levy/__init__.py
levy/config.py
levy/exceptions.py
levy/renderer.py
levy-0.6.1.dist-info/LICENSE
levy-0.6.1.dist-info/WHEEL
levy-0.6.1.dist-info/METADATA
levy-0.6.1.dist-info/RECORD
