Metadata-Version: 2.1
Name: levy
Version: 0.6.1
Summary: Dynamic python configuration parser
Home-page: https://github.com/pmbrull/levy
Author: pmbrull
Author-email: peremiquelbrull@gmail.com
Requires-Python: >=3.6
Classifier: Development Status :: 2 - Pre-Alpha
Classifier: Intended Audience :: Developers
Classifier: License :: OSI Approved :: MIT License
Classifier: Programming Language :: Python :: 3.7
Classifier: Programming Language :: Python :: 3.8
Classifier: Programming Language :: Python :: 3.9
Classifier: Topic :: Software Development :: Libraries :: Python Modules
Requires-Dist: PyYAML==5.4.1
Requires-Dist: Jinja2==3.0.1
Requires-Dist: pydantic==1.8.2
Requires-Dist: mkdocs >=1.1.2,<2.0.0 ; extra == "doc"
Requires-Dist: mkdocs-material >=5.4.0,<6.0.0 ; extra == "doc"
Requires-Dist: markdown-include >=0.5.1,<0.6.0 ; extra == "doc"
Requires-Dist: pytest >=6.2.4,<7.0.0 ; extra == "test"
Requires-Dist: coverage >=5.5,<6.0 ; extra == "test"
Requires-Dist: black >=21.5b1,<22.0b0 ; extra == "test"
Requires-Dist: isort >=5.9.3,<6.0.0 ; extra == "test"
Requires-Dist: pre-commit >= 2.9.2,<3.0.0 ; extra == "test"
Provides-Extra: doc
Provides-Extra: test
